{
  "info":"Central Bank of Myanmar",
  "description":"Official Website of Central Bank of Myanmar",
  "timestamp":1523232000,
  "rates":{
    "USD":"1,330.0",
    "VND":"5.8325",
    "THB":"42.687",
    "SEK":"158.52",
    "LKR":"8.5544",
    "ZAR":"110.53",
    "RSD":"13.827",
    "SAR":"354.63",
    "RUB":"22.888",
    "PHP":"25.569",
    "PKR":"11.487",
    "NOK":"169.86",
    "NZD":"969.18",
    "NPR":"12.792",
    "MYR":"344.25",
    "LAK":"16.034",
    "KWD":"4,426.8",
    "KRW":"124.51",
    "KES":"13.174",
    "ILS":"376.34",
    "IDR":"9.6604",
    "INR":"20.484",
    "HKD":"169.45",
    "EGP":"75.200",
    "DKK":"219.34",
    "CZK":"64.383",
    "CNY":"210.94",
    "CAD":"1,041.5",
    "KHR":"33.237",
    "BND":"1,008.5",
    "BRL":"394.54",
    "BDT":"16.019",
    "AUD":"1,023.1",
    "JPY":"1,244.4",
    "CHF":"1,385.8",
    "GBP":"1,874.3",
    "SGD":"1,012.0",
    "EUR":"1,632.3"
  }
}
