{
  "info":"Central Bank of Myanmar",
  "description":"Official Website of Central Bank of Myanmar",
  "timestamp":1525651200,
  "rates":{
    "USD":"1,343.0",
    "VND":"5.8989",
    "THB":"42.339",
    "SEK":"152.60",
    "LKR":"8.5201",
    "ZAR":"107.45",
    "RSD":"13.594",
    "SAR":"358.10",
    "RUB":"21.456",
    "PHP":"25.983",
    "PKR":"11.600",
    "NOK":"166.75",
    "NZD":"943.58",
    "NPR":"12.570",
    "MYR":"340.91",
    "LAK":"16.146",
    "KWD":"4,450.7",
    "KRW":"125.08",
    "KES":"13.397",
    "ILS":"371.73",
    "IDR":"9.6324",
    "INR":"20.099",
    "HKD":"171.09",
    "EGP":"76.178",
    "DKK":"215.64",
    "CZK":"63.079",
    "CNY":"211.07",
    "CAD":"1,044.9",
    "KHR":"33.166",
    "BND":"1,012.1",
    "BRL":"380.64",
    "BDT":"16.172",
    "AUD":"1,010.7",
    "JPY":"1,234.8",
    "CHF":"1,344.3",
    "GBP":"1,819.9",
    "SGD":"1,007.8",
    "EUR":"1,607.9"
  }
}
