{
  "info":"Central Bank of Myanmar",
  "description":"Official Website of Central Bank of Myanmar",
  "timestamp":1555891200,
  "rates":{
    "USD":"1,528.1",
    "VND":"6.5812",
    "THB":"47.963",
    "SEK":"164.14",
    "LKR":"8.7495",
    "ZAR":"108.29",
    "RSD":"14.568",
    "SAR":"407.48",
    "RUB":"23.961",
    "PHP":"29.404",
    "PKR":"10.787",
    "NOK":"179.70",
    "NZD":"1,020.7",
    "NPR":"13.724",
    "MYR":"369.42",
    "LAK":"17.754",
    "KWD":"5,023.2",
    "KRW":"133.89",
    "KES":"15.092",
    "ILS":"425.49",
    "IDR":"10.857",
    "INR":"21.959",
    "HKD":"194.78",
    "EGP":"89.167",
    "DKK":"230.17",
    "CZK":"66.878",
    "CNY":"227.65",
    "CAD":"1,143.8",
    "KHR":"37.366",
    "BND":"1,126.3",
    "BRL":"389.08",
    "BDT":"18.117",
    "AUD":"1,090.5",
    "JPY":"1,365.3",
    "CHF":"1,505.7",
    "GBP":"1,985.0",
    "SGD":"1,126.3",
    "EUR":"1,718.5"
  }
}
