{
  "info":"Central Bank of Myanmar",
  "description":"Official Website of Central Bank of Myanmar",
  "timestamp":1556841600,
  "rates":{
    "USD":"1,521.8",
    "VND":"6.5447",
    "THB":"47.504",
    "SEK":"158.86",
    "LKR":"8.5808",
    "ZAR":"104.57",
    "RSD":"14.399",
    "SAR":"405.78",
    "RUB":"23.279",
    "PHP":"29.335",
    "PKR":"10.747",
    "NOK":"173.60",
    "NZD":"1,006.8",
    "NPR":"13.720",
    "MYR":"367.36",
    "LAK":"17.516",
    "KWD":"5,003.3",
    "KRW":"130.05",
    "KES":"15.060",
    "ILS":"422.71",
    "IDR":"10.676",
    "INR":"21.949",
    "HKD":"193.99",
    "EGP":"88.606",
    "DKK":"227.52",
    "CZK":"66.099",
    "CNY":"225.97",
    "CAD":"1,130.5",
    "KHR":"37.501",
    "BND":"1,115.9",
    "BRL":"383.55",
    "BDT":"18.034",
    "AUD":"1,064.7",
    "JPY":"1,364.8",
    "CHF":"1,491.3",
    "GBP":"1,980.6",
    "SGD":"1,115.9",
    "EUR":"1,698.6"
  }
}
