{
  "info":"Central Bank of Myanmar",
  "description":"Official Website of Central Bank of Myanmar",
  "timestamp":1553472000,
  "rates":{
    "USD":"1,525.0",
    "VND":"6.5734",
    "THB":"48.290",
    "SEK":"165.33",
    "LKR":"8.5578",
    "ZAR":"105.52",
    "RSD":"14.623",
    "SAR":"406.64",
    "RUB":"23.683",
    "PHP":"29.059",
    "PKR":"10.847",
    "NOK":"178.83",
    "NZD":"1,048.8",
    "NPR":"13.845",
    "MYR":"374.83",
    "LAK":"17.751",
    "KWD":"5,025.1",
    "KRW":"134.51",
    "KES":"15.121",
    "ILS":"420.32",
    "IDR":"10.755",
    "INR":"22.151",
    "HKD":"194.31",
    "EGP":"88.176",
    "DKK":"231.23",
    "CZK":"67.080",
    "CNY":"227.28",
    "CAD":"1,137.1",
    "KHR":"37.983",
    "BND":"1,129.0",
    "BRL":"390.28",
    "BDT":"18.102",
    "AUD":"1,081.8",
    "JPY":"1,384.4",
    "CHF":"1,533.9",
    "GBP":"2,013.2",
    "SGD":"1,129.0",
    "EUR":"1,725.9"
  }
}
